kadi_apy/__init__.py
kadi_apy/globals.py
kadi_apy/cli/__init__.py
kadi_apy/cli/commons.py
kadi_apy/cli/core.py
kadi_apy/cli/decorators.py
kadi_apy/cli/main.py
kadi_apy/cli/search.py
kadi_apy/cli/commands/__init__.py
kadi_apy/cli/commands/collections.py
kadi_apy/cli/commands/config.py
kadi_apy/cli/commands/groups.py
kadi_apy/cli/commands/misc.py
kadi_apy/cli/commands/records.py
kadi_apy/cli/commands/templates.py
kadi_apy/cli/commands/users.py
kadi_apy/cli/commands/workflows.py
kadi_apy/cli/lib/__init__.py
kadi_apy/cli/lib/collections.py
kadi_apy/cli/lib/groups.py
kadi_apy/cli/lib/misc.py
kadi_apy/cli/lib/records.py
kadi_apy/cli/lib/templates.py
kadi_apy/cli/lib/users.py
kadi_apy/lib/__init__.py
kadi_apy/lib/commons.py
kadi_apy/lib/conversion.py
kadi_apy/lib/core.py
kadi_apy/lib/exceptions.py
kadi_apy/lib/imports.py
kadi_apy/lib/misc.py
kadi_apy/lib/resource.py
kadi_apy/lib/search.py
kadi_apy/lib/utils.py
kadi_apy/lib/resources/__init__.py
kadi_apy/lib/resources/collections.py
kadi_apy/lib/resources/groups.py
kadi_apy/lib/resources/records.py
kadi_apy/lib/resources/templates.py
kadi_apy/lib/resources/users.py
kadi_apy-0.48.1.dist-info/licenses/LICENSE
kadi_apy-0.48.1.dist-info/METADATA
kadi_apy-0.48.1.dist-info/WHEEL
kadi_apy-0.48.1.dist-info/entry_points.txt
kadi_apy-0.48.1.dist-info/top_level.txt
kadi_apy-0.48.1.dist-info/RECORD
