Metadata-Version: 2.4
Name: kadi-apy
Version: 0.48.1
Summary: API wrapper library for Kadi4Mat
Author: Karlsruhe Institute of Technology
License-Expression: Apache-2.0
Project-URL: Documentation, https://kadi-apy.readthedocs.io/en/stable
Project-URL: Source, https://gitlab.com/iam-cms/kadi-apy
Project-URL: Changelog, https://gitlab.com/iam-cms/kadi-apy/-/blob/master/HISTORY.md
Classifier: Development Status :: 4 - Beta
Classifier: Operating System :: OS Independent
Classifier: Programming Language :: Python :: 3
Requires-Python: <3.14,>=3.9
License-File: LICENSE
Requires-Dist: click<8.2.0,>=8.0.0
Requires-Dist: jsonref<2.0.0,>=1.1.0
Requires-Dist: python-dateutil<3.0.0,>=2.8.2
Requires-Dist: rdflib<8.0.0,>=7.0.0
Requires-Dist: niquests<4.0.0,>=3.13.0
Requires-Dist: xmlhelpy<0.15.0,>=0.14.0
Provides-Extra: dev
Requires-Dist: autoflake==2.3.1; extra == "dev"
Requires-Dist: black==25.1.0; extra == "dev"
Requires-Dist: build==1.2.2.post1; extra == "dev"
Requires-Dist: isort==6.0.1; extra == "dev"
Requires-Dist: myst-parser==3.0.1; extra == "dev"
Requires-Dist: pre-commit==4.0.1; extra == "dev"
Requires-Dist: pylint==3.3.7; extra == "dev"
Requires-Dist: Sphinx==7.4.7; extra == "dev"
Requires-Dist: sphinx-click==6.0.0; extra == "dev"
Requires-Dist: sphinx-rtd-theme==3.0.2; extra == "dev"
Requires-Dist: twine==6.1.0; extra == "dev"
Dynamic: license-file
